homer/__init__.py
homer/capirca.py
homer/cli.py
homer/config.py
homer/devices.py
homer/diff.py
homer/exceptions.py
homer/interactive.py
homer/netbox.py
homer/py.typed
homer/templates.py
homer/graphql/device_list.gql
homer/graphql/interface_list.gql
homer/graphql/interface_list_virtual_chassis.gql
homer/transports/__init__.py
homer/transports/json_rpc.py
homer/transports/junos.py
homer-0.11.0.dist-info/LICENSE
homer-0.11.0.dist-info/METADATA
homer-0.11.0.dist-info/WHEEL
homer-0.11.0.dist-info/entry_points.txt
homer-0.11.0.dist-info/top_level.txt
homer-0.11.0.dist-info/RECORD
