Metadata-Version: 2.1
Name: homer
Version: 0.11.0
Summary: Configuration manager for network devices
Home-page: https://gerrit.wikimedia.org/r/plugins/gitiles/operations/software/homer
Author: Riccardo Coccioli
Author-email: rcoccioli@wikimedia.org
License: GPLv3+
Keywords: network,switch,router,configuration,deploy
Platform: GNU/Linux
Classifier: Development Status :: 4 - Beta
Classifier: Environment :: Console
Classifier: Intended Audience :: System Administrators
Classifier: License :: OSI Approved :: GNU General Public License v3 or later (GPLv3+)
Classifier: Operating System :: MacOS :: MacOS X
Classifier: Operating System :: POSIX :: BSD
Classifier: Operating System :: POSIX :: Linux
Classifier: Programming Language :: Python :: 3.9
Classifier: Programming Language :: Python :: 3.10
Classifier: Programming Language :: Python :: 3.11
Classifier: Programming Language :: Python :: 3 :: Only
Classifier: Topic :: System :: Systems Administration
Classifier: Topic :: System :: Networking
Requires-Python: >=3.9
License-File: LICENSE
Requires-Dist: Jinja2 (>=2.10)
Requires-Dist: junos-eznc (<3,>=2.2.1)
Requires-Dist: paramiko
Requires-Dist: pynetbox
Requires-Dist: pyyaml (>=3.11)
Requires-Dist: aerleon
Requires-Dist: python-dateutil (>=2.8.1)
Requires-Dist: pytz (>=2021.1)
Provides-Extra: prospector
Requires-Dist: prospector[with_everything] (==1.16.1) ; extra == 'prospector'
Requires-Dist: pytest (>=3.3.0) ; extra == 'prospector'
Provides-Extra: tests
Requires-Dist: bandit (>=1.1.0) ; extra == 'tests'
Requires-Dist: flake8 (>=3.2.1) ; extra == 'tests'
Requires-Dist: flake8-import-order (>=0.18.1) ; extra == 'tests'
Requires-Dist: mypy (>=0.470) ; extra == 'tests'
Requires-Dist: pytest-cov (>=1.8.0) ; extra == 'tests'
Requires-Dist: pytest-xdist (>=1.15.0) ; extra == 'tests'
Requires-Dist: pytest (>=3.3.0) ; extra == 'tests'
Requires-Dist: requests-mock ; extra == 'tests'
Requires-Dist: sphinx-rtd-theme (>=0.1.6) ; extra == 'tests'
Requires-Dist: sphinx-argparse (>=0.1.15) ; extra == 'tests'
Requires-Dist: sphinx-autodoc-typehints (>=1.9.0) ; extra == 'tests'
Requires-Dist: Sphinx (>=1.4.9) ; extra == 'tests'
Requires-Dist: types-PyYAML ; extra == 'tests'
Requires-Dist: types-requests ; extra == 'tests'
